LICENSE
MANIFEST.in
README.md
setup.cfg
setup.py
mdconvert/README.ipynb
mdconvert/README.md
mdconvert/__init__.py
mdconvert/_version.py
mdconvert/mdconvertapp.py
mdconvert.egg-info/PKG-INFO
mdconvert.egg-info/SOURCES.txt
mdconvert.egg-info/dependency_links.txt
mdconvert.egg-info/entry_points.txt
mdconvert.egg-info/not-zip-safe
mdconvert.egg-info/top_level.txt
mdconvert/.ipynb_checkpoints/README-checkpoint.ipynb
mdconvert/bin/activate
mdconvert/bin/conda
mdconvert/bin/deactivate
tests/test_null.py
tests/fixtures/no-metadata.ipynb