Metadata-Version: 1.0
Name: mdconvert
Version: 0.1.0
Summary: configure nbconvert from ipynb
Home-page: UNKNOWN
Author: UNKNOWN
Author-email: UNKNOWN
License: BSD-3-Clause
Platform: UNKNOWN
